openapi_client_builder/__init__.py
openapi_client_builder/main.ipynb
openapi_client_builder/main.py
openapi_client_builder/tools/Schemas2type.py
openapi_client_builder/tools/Server2client.py
openapi_client_builder/tools/__init__.py
openapi_client_builder/tools/data_flow.py
openapi_client_builder/tools/template/nuxt.py
openapi_client_builder/tools/template.py
openapi_client_builder-0.1.42.dist-info/LICENSE
openapi_client_builder-0.1.42.dist-info/METADATA
openapi_client_builder-0.1.42.dist-info/WHEEL
openapi_client_builder-0.1.42.dist-info/entry_points.txt
openapi_client_builder-0.1.42.dist-info/RECORD
