Metadata-Version: 2.1
Name: openapi-client-builder
Version: 0.1.42
Summary: A tool that automatically generates client-side APIs based on the OpenAPI specification. Simplify the process of interacting with APIs by creating client libraries from OpenAPI definitions, enabling seamless integration and communication with backend services. The tool generates TypeScript request files and currently supports Nuxt framework, with plans to extend support to SvelteKit in the future.
Author: AnsonCar
Author-email: anson1tsang@gmail.com
Requires-Python: >=3.10,<4.0
Classifier: Programming Language :: Python :: 3
Classifier: Programming Language :: Python :: 3.10
Classifier: Programming Language :: Python :: 3.11
Classifier: Programming Language :: Python :: 3.12
Classifier: Programming Language :: Python :: 3.13
Requires-Dist: requests (>=2.32.3,<3.0.0)
Requires-Dist: typer (>=0.12.5,<0.13.0)
